odoo/addons/donation_bank_statement_oca/README.rst
odoo/addons/donation_bank_statement_oca/__init__.py
odoo/addons/donation_bank_statement_oca/__manifest__.py
odoo/addons/donation_bank_statement_oca/i18n/donation_bank_statement_oca.pot
odoo/addons/donation_bank_statement_oca/i18n/es.po
odoo/addons/donation_bank_statement_oca/i18n/it.po
odoo/addons/donation_bank_statement_oca/models/__init__.py
odoo/addons/donation_bank_statement_oca/models/account_bank_statement_line.py
odoo/addons/donation_bank_statement_oca/readme/CONTRIBUTORS.rst
odoo/addons/donation_bank_statement_oca/readme/DESCRIPTION.rst
odoo/addons/donation_bank_statement_oca/readme/USAGE.rst
odoo/addons/donation_bank_statement_oca/static/description/donation_bank_statement1.png
odoo/addons/donation_bank_statement_oca/static/description/donation_bank_statement2.png
odoo/addons/donation_bank_statement_oca/static/description/icon.png
odoo/addons/donation_bank_statement_oca/static/description/index.html
odoo/addons/donation_bank_statement_oca/views/account_bank_statement_line.xml
odoo_addon_donation_bank_statement_oca-16.0.1.0.0.8.dist-info/METADATA
odoo_addon_donation_bank_statement_oca-16.0.1.0.0.8.dist-info/WHEEL
odoo_addon_donation_bank_statement_oca-16.0.1.0.0.8.dist-info/top_level.txt
odoo_addon_donation_bank_statement_oca-16.0.1.0.0.8.dist-info/RECORD
