Metadata-Version: 2.1
Name: odoo-addon-donation-bank-statement-oca
Version: 16.0.1.0.0.8
Summary: Manage donations by credit transfer
Home-page: https://github.com/OCA/donation
Author: Akretion, Odoo Community Association (OCA)
Author-email: support@odoo-community.org
License: AGPL-3
Platform: UNKNOWN
Classifier: Programming Language :: Python
Classifier: Framework :: Odoo
Classifier: Framework :: Odoo :: 16.0
Classifier: License :: OSI Approved :: GNU Affero General Public License v3
Requires-Python: >=3.10
Requires-Dist: odoo-addon-account-reconcile-oca <16.1dev,>=16.0dev
Requires-Dist: odoo-addon-donation <16.1dev,>=16.0dev
Requires-Dist: odoo <16.1dev,>=16.0a
